{
  "objects": {
    "calls": 4,
    "execution_time": 0.0,
    "call_sites": {
      "solvers.py:2703": {
        "count": 1,
        "signatures": [
          {
            "type_signature": "objects(tuple, bool, bool, bool)",
            "value_signature": "objects(tuple(len=7), True, True, True)"
          }
        ],
        "code_context": "x1 = objects(I, T, T, T)"
      }
    },
    "type_signatures": [
      "objects(tuple, bool, bool, bool)"
    ],
    "value_signatures": [
      "objects(tuple(len=7), True, True, True)"
    ]
  },
  "mostcolor_t": {
    "calls": 4,
    "execution_time": 0.0,
    "call_sites": {
      "solvers.py:2703": {
        "count": 1,
        "signatures": [
          {
            "type_signature": "mostcolor_t(tuple)",
            "value_signature": "mostcolor_t(tuple(len=7))"
          }
        ],
        "code_context": "x1 = objects(I, T, T, T)"
      }
    },
    "type_signatures": [
      "mostcolor_t(tuple)"
    ],
    "value_signatures": [
      "mostcolor_t(tuple(len=7))"
    ]
  },
  "asindices": {
    "calls": 4,
    "execution_time": 0.0,
    "call_sites": {
      "solvers.py:2703": {
        "count": 1,
        "signatures": [
          {
            "type_signature": "asindices(tuple)",
            "value_signature": "asindices(tuple(len=7))"
          }
        ],
        "code_context": "x1 = objects(I, T, T, T)"
      }
    },
    "type_signatures": [
      "asindices(tuple)"
    ],
    "value_signatures": [
      "asindices(tuple(len=7))"
    ]
  },
  "neighbors": {
    "calls": 80,
    "execution_time": 0.0,
    "call_sites": {
      "solvers.py:2703": {
        "count": 38,
        "signatures": [
          {
            "type_signature": "neighbors(tuple)",
            "value_signature": "neighbors((5, 4))"
          },
          {
            "type_signature": "neighbors(tuple)",
            "value_signature": "neighbors((4, 5))"
          },
          {
            "type_signature": "neighbors(tuple)",
            "value_signature": "neighbors((6, 3))"
          },
          {
            "type_signature": "neighbors(tuple)",
            "value_signature": "neighbors((3, 6))"
          },
          {
            "type_signature": "neighbors(tuple)",
            "value_signature": "neighbors((4, 6))"
          },
          {
            "type_signature": "neighbors(tuple)",
            "value_signature": "neighbors((5, 5))"
          },
          {
            "type_signature": "neighbors(tuple)",
            "value_signature": "neighbors((6, 4))"
          },
          {
            "type_signature": "neighbors(tuple)",
            "value_signature": "neighbors((6, 2))"
          },
          {
            "type_signature": "neighbors(tuple)",
            "value_signature": "neighbors((5, 3))"
          },
          {
            "type_signature": "neighbors(tuple)",
            "value_signature": "neighbors((4, 4))"
          },
          {
            "type_signature": "neighbors(tuple)",
            "value_signature": "neighbors((3, 5))"
          },
          {
            "type_signature": "neighbors(tuple)",
            "value_signature": "neighbors((2, 6))"
          },
          {
            "type_signature": "neighbors(tuple)",
            "value_signature": "neighbors((0, 2))"
          },
          {
            "type_signature": "neighbors(tuple)",
            "value_signature": "neighbors((1, 1))"
          },
          {
            "type_signature": "neighbors(tuple)",
            "value_signature": "neighbors((2, 0))"
          },
          {
            "type_signature": "neighbors(tuple)",
            "value_signature": "neighbors((1, 0))"
          },
          {
            "type_signature": "neighbors(tuple)",
            "value_signature": "neighbors((0, 1))"
          },
          {
            "type_signature": "neighbors(tuple)",
            "value_signature": "neighbors((0, 0))"
          },
          {
            "type_signature": "neighbors(tuple)",
            "value_signature": "neighbors((4, 0))"
          },
          {
            "type_signature": "neighbors(tuple)",
            "value_signature": "neighbors((3, 1))"
          },
          {
            "type_signature": "neighbors(tuple)",
            "value_signature": "neighbors((2, 2))"
          },
          {
            "type_signature": "neighbors(tuple)",
            "value_signature": "neighbors((1, 3))"
          },
          {
            "type_signature": "neighbors(tuple)",
            "value_signature": "neighbors((0, 4))"
          },
          {
            "type_signature": "neighbors(tuple)",
            "value_signature": "neighbors((0, 5))"
          },
          {
            "type_signature": "neighbors(tuple)",
            "value_signature": "neighbors((1, 4))"
          },
          {
            "type_signature": "neighbors(tuple)",
            "value_signature": "neighbors((2, 3))"
          },
          {
            "type_signature": "neighbors(tuple)",
            "value_signature": "neighbors((3, 2))"
          },
          {
            "type_signature": "neighbors(tuple)",
            "value_signature": "neighbors((4, 1))"
          },
          {
            "type_signature": "neighbors(tuple)",
            "value_signature": "neighbors((5, 0))"
          },
          {
            "type_signature": "neighbors(tuple)",
            "value_signature": "neighbors((5, 1))"
          },
          {
            "type_signature": "neighbors(tuple)",
            "value_signature": "neighbors((4, 2))"
          },
          {
            "type_signature": "neighbors(tuple)",
            "value_signature": "neighbors((6, 0))"
          },
          {
            "type_signature": "neighbors(tuple)",
            "value_signature": "neighbors((3, 3))"
          },
          {
            "type_signature": "neighbors(tuple)",
            "value_signature": "neighbors((2, 4))"
          },
          {
            "type_signature": "neighbors(tuple)",
            "value_signature": "neighbors((1, 5))"
          },
          {
            "type_signature": "neighbors(tuple)",
            "value_signature": "neighbors((0, 6))"
          },
          {
            "type_signature": "neighbors(tuple)",
            "value_signature": "neighbors((6, 5))"
          },
          {
            "type_signature": "neighbors(tuple)",
            "value_signature": "neighbors((5, 6))"
          }
        ],
        "code_context": "x1 = objects(I, T, T, T)"
      },
      "solvers.py:2704": {
        "count": 1,
        "signatures": [
          {
            "type_signature": "neighbors(tuple)",
            "value_signature": "neighbors((0, 0))"
          }
        ],
        "code_context": "x2 = neighbors(ORIGIN)"
      },
      "solvers.py:2705": {
        "count": 8,
        "signatures": [
          {
            "type_signature": "neighbors(tuple)",
            "value_signature": "neighbors((0, 1))"
          },
          {
            "type_signature": "neighbors(tuple)",
            "value_signature": "neighbors((-1, -1))"
          },
          {
            "type_signature": "neighbors(tuple)",
            "value_signature": "neighbors((-1, 1))"
          },
          {
            "type_signature": "neighbors(tuple)",
            "value_signature": "neighbors((1, 1))"
          },
          {
            "type_signature": "neighbors(tuple)",
            "value_signature": "neighbors((1, -1))"
          },
          {
            "type_signature": "neighbors(tuple)",
            "value_signature": "neighbors((-1, 0))"
          },
          {
            "type_signature": "neighbors(tuple)",
            "value_signature": "neighbors((1, 0))"
          },
          {
            "type_signature": "neighbors(tuple)",
            "value_signature": "neighbors((0, -1))"
          }
        ],
        "code_context": "x3 = mapply(neighbors, x2)"
      }
    },
    "type_signatures": [
      "neighbors(tuple)"
    ],
    "value_signatures": [
      "neighbors((0, 0))",
      "neighbors((0, 6))",
      "neighbors((0, 4))",
      "neighbors((5, 3))",
      "neighbors((6, 5))",
      "neighbors((-1, 1))",
      "neighbors((4, 1))",
      "neighbors((3, 2))",
      "neighbors((4, 4))",
      "neighbors((2, 6))",
      "neighbors((1, 4))",
      "neighbors((1, 0))",
      "neighbors((3, 6))",
      "neighbors((0, 5))",
      "neighbors((2, 0))",
      "neighbors((1, -1))",
      "neighbors((-1, -1))",
      "neighbors((4, 0))",
      "neighbors((3, 3))",
      "neighbors((5, 4))",
      "neighbors((4, 2))",
      "neighbors((6, 2))",
      "neighbors((5, 6))",
      "neighbors((0, 1))",
      "neighbors((0, -1))",
      "neighbors((3, 5))",
      "neighbors((1, 1))",
      "neighbors((5, 5))",
      "neighbors((0, 2))",
      "neighbors((6, 4))",
      "neighbors((6, 3))",
      "neighbors((4, 5))",
      "neighbors((1, 3))",
      "neighbors((5, 1))",
      "neighbors((2, 2))",
      "neighbors((2, 4))",
      "neighbors((1, 5))",
      "neighbors((3, 1))",
      "neighbors((2, 3))",
      "neighbors((5, 0))",
      "neighbors((6, 0))",
      "neighbors((4, 6))",
      "neighbors((-1, 0))"
    ]
  },
  "dneighbors": {
    "calls": 80,
    "execution_time": 0.0,
    "call_sites": {
      "solvers.py:2703": {
        "count": 38,
        "signatures": [
          {
            "type_signature": "dneighbors(tuple)",
            "value_signature": "dneighbors((5, 4))"
          },
          {
            "type_signature": "dneighbors(tuple)",
            "value_signature": "dneighbors((4, 5))"
          },
          {
            "type_signature": "dneighbors(tuple)",
            "value_signature": "dneighbors((6, 3))"
          },
          {
            "type_signature": "dneighbors(tuple)",
            "value_signature": "dneighbors((3, 6))"
          },
          {
            "type_signature": "dneighbors(tuple)",
            "value_signature": "dneighbors((4, 6))"
          },
          {
            "type_signature": "dneighbors(tuple)",
            "value_signature": "dneighbors((5, 5))"
          },
          {
            "type_signature": "dneighbors(tuple)",
            "value_signature": "dneighbors((6, 4))"
          },
          {
            "type_signature": "dneighbors(tuple)",
            "value_signature": "dneighbors((6, 2))"
          },
          {
            "type_signature": "dneighbors(tuple)",
            "value_signature": "dneighbors((5, 3))"
          },
          {
            "type_signature": "dneighbors(tuple)",
            "value_signature": "dneighbors((4, 4))"
          },
          {
            "type_signature": "dneighbors(tuple)",
            "value_signature": "dneighbors((3, 5))"
          },
          {
            "type_signature": "dneighbors(tuple)",
            "value_signature": "dneighbors((2, 6))"
          },
          {
            "type_signature": "dneighbors(tuple)",
            "value_signature": "dneighbors((0, 2))"
          },
          {
            "type_signature": "dneighbors(tuple)",
            "value_signature": "dneighbors((1, 1))"
          },
          {
            "type_signature": "dneighbors(tuple)",
            "value_signature": "dneighbors((2, 0))"
          },
          {
            "type_signature": "dneighbors(tuple)",
            "value_signature": "dneighbors((1, 0))"
          },
          {
            "type_signature": "dneighbors(tuple)",
            "value_signature": "dneighbors((0, 1))"
          },
          {
            "type_signature": "dneighbors(tuple)",
            "value_signature": "dneighbors((0, 0))"
          },
          {
            "type_signature": "dneighbors(tuple)",
            "value_signature": "dneighbors((4, 0))"
          },
          {
            "type_signature": "dneighbors(tuple)",
            "value_signature": "dneighbors((3, 1))"
          },
          {
            "type_signature": "dneighbors(tuple)",
            "value_signature": "dneighbors((2, 2))"
          },
          {
            "type_signature": "dneighbors(tuple)",
            "value_signature": "dneighbors((1, 3))"
          },
          {
            "type_signature": "dneighbors(tuple)",
            "value_signature": "dneighbors((0, 4))"
          },
          {
            "type_signature": "dneighbors(tuple)",
            "value_signature": "dneighbors((0, 5))"
          },
          {
            "type_signature": "dneighbors(tuple)",
            "value_signature": "dneighbors((1, 4))"
          },
          {
            "type_signature": "dneighbors(tuple)",
            "value_signature": "dneighbors((2, 3))"
          },
          {
            "type_signature": "dneighbors(tuple)",
            "value_signature": "dneighbors((3, 2))"
          },
          {
            "type_signature": "dneighbors(tuple)",
            "value_signature": "dneighbors((4, 1))"
          },
          {
            "type_signature": "dneighbors(tuple)",
            "value_signature": "dneighbors((5, 0))"
          },
          {
            "type_signature": "dneighbors(tuple)",
            "value_signature": "dneighbors((5, 1))"
          },
          {
            "type_signature": "dneighbors(tuple)",
            "value_signature": "dneighbors((4, 2))"
          },
          {
            "type_signature": "dneighbors(tuple)",
            "value_signature": "dneighbors((6, 0))"
          },
          {
            "type_signature": "dneighbors(tuple)",
            "value_signature": "dneighbors((3, 3))"
          },
          {
            "type_signature": "dneighbors(tuple)",
            "value_signature": "dneighbors((2, 4))"
          },
          {
            "type_signature": "dneighbors(tuple)",
            "value_signature": "dneighbors((1, 5))"
          },
          {
            "type_signature": "dneighbors(tuple)",
            "value_signature": "dneighbors((0, 6))"
          },
          {
            "type_signature": "dneighbors(tuple)",
            "value_signature": "dneighbors((6, 5))"
          },
          {
            "type_signature": "dneighbors(tuple)",
            "value_signature": "dneighbors((5, 6))"
          }
        ],
        "code_context": "x1 = objects(I, T, T, T)"
      },
      "solvers.py:2704": {
        "count": 1,
        "signatures": [
          {
            "type_signature": "dneighbors(tuple)",
            "value_signature": "dneighbors((0, 0))"
          }
        ],
        "code_context": "x2 = neighbors(ORIGIN)"
      },
      "solvers.py:2705": {
        "count": 8,
        "signatures": [
          {
            "type_signature": "dneighbors(tuple)",
            "value_signature": "dneighbors((0, 1))"
          },
          {
            "type_signature": "dneighbors(tuple)",
            "value_signature": "dneighbors((-1, -1))"
          },
          {
            "type_signature": "dneighbors(tuple)",
            "value_signature": "dneighbors((-1, 1))"
          },
          {
            "type_signature": "dneighbors(tuple)",
            "value_signature": "dneighbors((1, 1))"
          },
          {
            "type_signature": "dneighbors(tuple)",
            "value_signature": "dneighbors((1, -1))"
          },
          {
            "type_signature": "dneighbors(tuple)",
            "value_signature": "dneighbors((-1, 0))"
          },
          {
            "type_signature": "dneighbors(tuple)",
            "value_signature": "dneighbors((1, 0))"
          },
          {
            "type_signature": "dneighbors(tuple)",
            "value_signature": "dneighbors((0, -1))"
          }
        ],
        "code_context": "x3 = mapply(neighbors, x2)"
      }
    },
    "type_signatures": [
      "dneighbors(tuple)"
    ],
    "value_signatures": [
      "dneighbors((5, 3))",
      "dneighbors((5, 0))",
      "dneighbors((0, 4))",
      "dneighbors((4, 1))",
      "dneighbors((2, 6))",
      "dneighbors((5, 6))",
      "dneighbors((0, 5))",
      "dneighbors((0, 6))",
      "dneighbors((2, 4))",
      "dneighbors((6, 3))",
      "dneighbors((2, 0))",
      "dneighbors((6, 4))",
      "dneighbors((4, 2))",
      "dneighbors((4, 4))",
      "dneighbors((0, 0))",
      "dneighbors((-1, 1))",
      "dneighbors((1, 1))",
      "dneighbors((3, 1))",
      "dneighbors((3, 3))",
      "dneighbors((1, 3))",
      "dneighbors((1, 4))",
      "dneighbors((1, 5))",
      "dneighbors((5, 1))",
      "dneighbors((0, 2))",
      "dneighbors((-1, 0))",
      "dneighbors((2, 2))",
      "dneighbors((6, 5))",
      "dneighbors((1, 0))",
      "dneighbors((4, 5))",
      "dneighbors((3, 5))",
      "dneighbors((1, -1))",
      "dneighbors((0, -1))",
      "dneighbors((-1, -1))",
      "dneighbors((3, 2))",
      "dneighbors((5, 5))",
      "dneighbors((6, 0))",
      "dneighbors((5, 4))",
      "dneighbors((4, 0))",
      "dneighbors((3, 6))",
      "dneighbors((4, 6))",
      "dneighbors((2, 3))",
      "dneighbors((6, 2))",
      "dneighbors((0, 1))"
    ]
  },
  "ineighbors": {
    "calls": 80,
    "execution_time": 0.0,
    "call_sites": {
      "solvers.py:2703": {
        "count": 38,
        "signatures": [
          {
            "type_signature": "ineighbors(tuple)",
            "value_signature": "ineighbors((5, 4))"
          },
          {
            "type_signature": "ineighbors(tuple)",
            "value_signature": "ineighbors((4, 5))"
          },
          {
            "type_signature": "ineighbors(tuple)",
            "value_signature": "ineighbors((6, 3))"
          },
          {
            "type_signature": "ineighbors(tuple)",
            "value_signature": "ineighbors((3, 6))"
          },
          {
            "type_signature": "ineighbors(tuple)",
            "value_signature": "ineighbors((4, 6))"
          },
          {
            "type_signature": "ineighbors(tuple)",
            "value_signature": "ineighbors((5, 5))"
          },
          {
            "type_signature": "ineighbors(tuple)",
            "value_signature": "ineighbors((6, 4))"
          },
          {
            "type_signature": "ineighbors(tuple)",
            "value_signature": "ineighbors((6, 2))"
          },
          {
            "type_signature": "ineighbors(tuple)",
            "value_signature": "ineighbors((5, 3))"
          },
          {
            "type_signature": "ineighbors(tuple)",
            "value_signature": "ineighbors((4, 4))"
          },
          {
            "type_signature": "ineighbors(tuple)",
            "value_signature": "ineighbors((3, 5))"
          },
          {
            "type_signature": "ineighbors(tuple)",
            "value_signature": "ineighbors((2, 6))"
          },
          {
            "type_signature": "ineighbors(tuple)",
            "value_signature": "ineighbors((0, 2))"
          },
          {
            "type_signature": "ineighbors(tuple)",
            "value_signature": "ineighbors((1, 1))"
          },
          {
            "type_signature": "ineighbors(tuple)",
            "value_signature": "ineighbors((2, 0))"
          },
          {
            "type_signature": "ineighbors(tuple)",
            "value_signature": "ineighbors((1, 0))"
          },
          {
            "type_signature": "ineighbors(tuple)",
            "value_signature": "ineighbors((0, 1))"
          },
          {
            "type_signature": "ineighbors(tuple)",
            "value_signature": "ineighbors((0, 0))"
          },
          {
            "type_signature": "ineighbors(tuple)",
            "value_signature": "ineighbors((4, 0))"
          },
          {
            "type_signature": "ineighbors(tuple)",
            "value_signature": "ineighbors((3, 1))"
          },
          {
            "type_signature": "ineighbors(tuple)",
            "value_signature": "ineighbors((2, 2))"
          },
          {
            "type_signature": "ineighbors(tuple)",
            "value_signature": "ineighbors((1, 3))"
          },
          {
            "type_signature": "ineighbors(tuple)",
            "value_signature": "ineighbors((0, 4))"
          },
          {
            "type_signature": "ineighbors(tuple)",
            "value_signature": "ineighbors((0, 5))"
          },
          {
            "type_signature": "ineighbors(tuple)",
            "value_signature": "ineighbors((1, 4))"
          },
          {
            "type_signature": "ineighbors(tuple)",
            "value_signature": "ineighbors((2, 3))"
          },
          {
            "type_signature": "ineighbors(tuple)",
            "value_signature": "ineighbors((3, 2))"
          },
          {
            "type_signature": "ineighbors(tuple)",
            "value_signature": "ineighbors((4, 1))"
          },
          {
            "type_signature": "ineighbors(tuple)",
            "value_signature": "ineighbors((5, 0))"
          },
          {
            "type_signature": "ineighbors(tuple)",
            "value_signature": "ineighbors((5, 1))"
          },
          {
            "type_signature": "ineighbors(tuple)",
            "value_signature": "ineighbors((4, 2))"
          },
          {
            "type_signature": "ineighbors(tuple)",
            "value_signature": "ineighbors((6, 0))"
          },
          {
            "type_signature": "ineighbors(tuple)",
            "value_signature": "ineighbors((3, 3))"
          },
          {
            "type_signature": "ineighbors(tuple)",
            "value_signature": "ineighbors((2, 4))"
          },
          {
            "type_signature": "ineighbors(tuple)",
            "value_signature": "ineighbors((1, 5))"
          },
          {
            "type_signature": "ineighbors(tuple)",
            "value_signature": "ineighbors((0, 6))"
          },
          {
            "type_signature": "ineighbors(tuple)",
            "value_signature": "ineighbors((6, 5))"
          },
          {
            "type_signature": "ineighbors(tuple)",
            "value_signature": "ineighbors((5, 6))"
          }
        ],
        "code_context": "x1 = objects(I, T, T, T)"
      },
      "solvers.py:2704": {
        "count": 1,
        "signatures": [
          {
            "type_signature": "ineighbors(tuple)",
            "value_signature": "ineighbors((0, 0))"
          }
        ],
        "code_context": "x2 = neighbors(ORIGIN)"
      },
      "solvers.py:2705": {
        "count": 8,
        "signatures": [
          {
            "type_signature": "ineighbors(tuple)",
            "value_signature": "ineighbors((0, 1))"
          },
          {
            "type_signature": "ineighbors(tuple)",
            "value_signature": "ineighbors((-1, -1))"
          },
          {
            "type_signature": "ineighbors(tuple)",
            "value_signature": "ineighbors((-1, 1))"
          },
          {
            "type_signature": "ineighbors(tuple)",
            "value_signature": "ineighbors((1, 1))"
          },
          {
            "type_signature": "ineighbors(tuple)",
            "value_signature": "ineighbors((1, -1))"
          },
          {
            "type_signature": "ineighbors(tuple)",
            "value_signature": "ineighbors((-1, 0))"
          },
          {
            "type_signature": "ineighbors(tuple)",
            "value_signature": "ineighbors((1, 0))"
          },
          {
            "type_signature": "ineighbors(tuple)",
            "value_signature": "ineighbors((0, -1))"
          }
        ],
        "code_context": "x3 = mapply(neighbors, x2)"
      }
    },
    "type_signatures": [
      "ineighbors(tuple)"
    ],
    "value_signatures": [
      "ineighbors((5, 5))",
      "ineighbors((2, 0))",
      "ineighbors((1, 3))",
      "ineighbors((4, 1))",
      "ineighbors((3, 1))",
      "ineighbors((4, 0))",
      "ineighbors((4, 6))",
      "ineighbors((0, 6))",
      "ineighbors((2, 2))",
      "ineighbors((6, 3))",
      "ineighbors((2, 6))",
      "ineighbors((1, 4))",
      "ineighbors((-1, -1))",
      "ineighbors((0, 4))",
      "ineighbors((3, 2))",
      "ineighbors((1, 5))",
      "ineighbors((2, 4))",
      "ineighbors((5, 4))",
      "ineighbors((5, 0))",
      "ineighbors((6, 5))",
      "ineighbors((1, -1))",
      "ineighbors((6, 2))",
      "ineighbors((3, 6))",
      "ineighbors((1, 1))",
      "ineighbors((4, 2))",
      "ineighbors((5, 3))",
      "ineighbors((6, 4))",
      "ineighbors((5, 6))",
      "ineighbors((0, 5))",
      "ineighbors((0, 1))",
      "ineighbors((3, 5))",
      "ineighbors((5, 1))",
      "ineighbors((6, 0))",
      "ineighbors((3, 3))",
      "ineighbors((1, 0))",
      "ineighbors((0, -1))",
      "ineighbors((4, 5))",
      "ineighbors((2, 3))",
      "ineighbors((-1, 0))",
      "ineighbors((0, 2))",
      "ineighbors((4, 4))",
      "ineighbors((-1, 1))",
      "ineighbors((0, 0))"
    ]
  },
  "mapply": {
    "calls": 8,
    "execution_time": 0.0,
    "call_sites": {
      "solvers.py:2705": {
        "count": 1,
        "signatures": [
          {
            "type_signature": "mapply(function, frozenset)",
            "value_signature": "mapply(<function neighbors at 0x10079aca0>, frozenset(len=8))"
          }
        ],
        "code_context": "x3 = mapply(neighbors, x2)"
      },
      "solvers.py:2710": {
        "count": 4,
        "signatures": [
          {
            "type_signature": "mapply(function, frozenset)",
            "value_signature": "mapply(<function lbind.<locals>.<lambda> at 0x100c9b040>, frozenset(len=25))"
          },
          {
            "type_signature": "mapply(function, frozenset)",
            "value_signature": "mapply(<function lbind.<locals>.<lambda> at 0x100cba040>, frozenset(len=25))"
          },
          {
            "type_signature": "mapply(function, frozenset)",
            "value_signature": "mapply(<function lbind.<locals>.<lambda> at 0x100cc5040>, frozenset(len=25))"
          },
          {
            "type_signature": "mapply(function, frozenset)",
            "value_signature": "mapply(<function lbind.<locals>.<lambda> at 0x100ccf040>, frozenset(len=25))"
          }
        ],
        "code_context": "x8 = mapply(x7, x5)"
      }
    },
    "type_signatures": [
      "mapply(function, frozenset)"
    ],
    "value_signatures": [
      "mapply(<function neighbors at 0x10079aca0>, frozenset(len=8))",
      "mapply(<function lbind.<locals>.<lambda> at 0x100cc5040>, frozenset(len=25))",
      "mapply(<function lbind.<locals>.<lambda> at 0x100c9b040>, frozenset(len=25))",
      "mapply(<function lbind.<locals>.<lambda> at 0x100ccf040>, frozenset(len=25))",
      "mapply(<function lbind.<locals>.<lambda> at 0x100cba040>, frozenset(len=25))"
    ]
  },
  "apply": {
    "calls": 12,
    "execution_time": 0.0,
    "call_sites": {
      "solvers.py:2705": {
        "count": 1,
        "signatures": [
          {
            "type_signature": "apply(function, frozenset)",
            "value_signature": "apply(<function neighbors at 0x10079aca0>, frozenset(len=8))"
          }
        ],
        "code_context": "x3 = mapply(neighbors, x2)"
      },
      "solvers.py:2707": {
        "count": 1,
        "signatures": [
          {
            "type_signature": "apply(function, frozenset)",
            "value_signature": "apply(<function rbind.<locals>.<lambda> at 0x100c76f70>, frozenset(len=25))"
          }
        ],
        "code_context": "x5 = apply(x4, x3)"
      },
      "solvers.py:2710": {
        "count": 4,
        "signatures": [
          {
            "type_signature": "apply(function, frozenset)",
            "value_signature": "apply(<function lbind.<locals>.<lambda> at 0x100c9b040>, frozenset(len=25))"
          },
          {
            "type_signature": "apply(function, frozenset)",
            "value_signature": "apply(<function lbind.<locals>.<lambda> at 0x100cba040>, frozenset(len=25))"
          },
          {
            "type_signature": "apply(function, frozenset)",
            "value_signature": "apply(<function lbind.<locals>.<lambda> at 0x100cc5040>, frozenset(len=25))"
          },
          {
            "type_signature": "apply(function, frozenset)",
            "value_signature": "apply(<function lbind.<locals>.<lambda> at 0x100ccf040>, frozenset(len=25))"
          }
        ],
        "code_context": "x8 = mapply(x7, x5)"
      }
    },
    "type_signatures": [
      "apply(function, frozenset)"
    ],
    "value_signatures": [
      "apply(<function rbind.<locals>.<lambda> at 0x100c76f70>, frozenset(len=25))",
      "apply(<function neighbors at 0x10079aca0>, frozenset(len=8))",
      "apply(<function lbind.<locals>.<lambda> at 0x100cc5040>, frozenset(len=25))",
      "apply(<function lbind.<locals>.<lambda> at 0x100ccf040>, frozenset(len=25))",
      "apply(<function lbind.<locals>.<lambda> at 0x100cba040>, frozenset(len=25))",
      "apply(<function lbind.<locals>.<lambda> at 0x100c9b040>, frozenset(len=25))"
    ]
  },
  "merge": {
    "calls": 8,
    "execution_time": 0.0,
    "call_sites": {
      "solvers.py:2705": {
        "count": 1,
        "signatures": [
          {
            "type_signature": "merge(frozenset)",
            "value_signature": "merge(frozenset(len=8))"
          }
        ],
        "code_context": "x3 = mapply(neighbors, x2)"
      },
      "solvers.py:2710": {
        "count": 1,
        "signatures": [
          {
            "type_signature": "merge(frozenset)",
            "value_signature": "merge(frozenset(len=25))"
          }
        ],
        "code_context": "x8 = mapply(x7, x5)"
      }
    },
    "type_signatures": [
      "merge(frozenset)"
    ],
    "value_signatures": [
      "merge(frozenset(len=25))",
      "merge(frozenset(len=8))"
    ]
  },
  "rbind": {
    "calls": 4,
    "execution_time": 0.0,
    "call_sites": {
      "solvers.py:2706": {
        "count": 1,
        "signatures": [
          {
            "type_signature": "rbind(function, int)",
            "value_signature": "rbind(<function multiply at 0x10079ac10>, 3)"
          }
        ],
        "code_context": "x4 = rbind(multiply, THREE)"
      }
    },
    "type_signatures": [
      "rbind(function, int)"
    ],
    "value_signatures": [
      "rbind(<function multiply at 0x10079ac10>, 3)"
    ]
  },
  "multiply": {
    "calls": 100,
    "execution_time": 0.0,
    "call_sites": {
      "solvers.py:2707": {
        "count": 25,
        "signatures": [
          {
            "type_signature": "multiply(tuple, int)",
            "value_signature": "multiply((0, 2), 3)"
          },
          {
            "type_signature": "multiply(tuple, int)",
            "value_signature": "multiply((2, 2), 3)"
          },
          {
            "type_signature": "multiply(tuple, int)",
            "value_signature": "multiply((1, 0), 3)"
          },
          {
            "type_signature": "multiply(tuple, int)",
            "value_signature": "multiply((-1, -1), 3)"
          },
          {
            "type_signature": "multiply(tuple, int)",
            "value_signature": "multiply((-2, -1), 3)"
          },
          {
            "type_signature": "multiply(tuple, int)",
            "value_signature": "multiply((-1, -2), 3)"
          },
          {
            "type_signature": "multiply(tuple, int)",
            "value_signature": "multiply((-2, -2), 3)"
          },
          {
            "type_signature": "multiply(tuple, int)",
            "value_signature": "multiply((-1, 1), 3)"
          },
          {
            "type_signature": "multiply(tuple, int)",
            "value_signature": "multiply((-2, 1), 3)"
          },
          {
            "type_signature": "multiply(tuple, int)",
            "value_signature": "multiply((0, -1), 3)"
          },
          {
            "type_signature": "multiply(tuple, int)",
            "value_signature": "multiply((0, -2), 3)"
          },
          {
            "type_signature": "multiply(tuple, int)",
            "value_signature": "multiply((0, 1), 3)"
          },
          {
            "type_signature": "multiply(tuple, int)",
            "value_signature": "multiply((2, -1), 3)"
          },
          {
            "type_signature": "multiply(tuple, int)",
            "value_signature": "multiply((2, -2), 3)"
          },
          {
            "type_signature": "multiply(tuple, int)",
            "value_signature": "multiply((1, 2), 3)"
          },
          {
            "type_signature": "multiply(tuple, int)",
            "value_signature": "multiply((2, 1), 3)"
          },
          {
            "type_signature": "multiply(tuple, int)",
            "value_signature": "multiply((-2, 0), 3)"
          },
          {
            "type_signature": "multiply(tuple, int)",
            "value_signature": "multiply((-1, 0), 3)"
          },
          {
            "type_signature": "multiply(tuple, int)",
            "value_signature": "multiply((-2, 2), 3)"
          },
          {
            "type_signature": "multiply(tuple, int)",
            "value_signature": "multiply((0, 0), 3)"
          },
          {
            "type_signature": "multiply(tuple, int)",
            "value_signature": "multiply((1, 1), 3)"
          },
          {
            "type_signature": "multiply(tuple, int)",
            "value_signature": "multiply((2, 0), 3)"
          },
          {
            "type_signature": "multiply(tuple, int)",
            "value_signature": "multiply((1, -2), 3)"
          },
          {
            "type_signature": "multiply(tuple, int)",
            "value_signature": "multiply((1, -1), 3)"
          },
          {
            "type_signature": "multiply(tuple, int)",
            "value_signature": "multiply((-1, 2), 3)"
          }
        ],
        "code_context": "x5 = apply(x4, x3)"
      }
    },
    "type_signatures": [
      "multiply(tuple, int)"
    ],
    "value_signatures": [
      "multiply((2, 2), 3)",
      "multiply((-2, 1), 3)",
      "multiply((2, -2), 3)",
      "multiply((1, 1), 3)",
      "multiply((0, -2), 3)",
      "multiply((2, 0), 3)",
      "multiply((-2, -1), 3)",
      "multiply((1, 0), 3)",
      "multiply((0, 1), 3)",
      "multiply((-1, 0), 3)",
      "multiply((1, -2), 3)",
      "multiply((2, -1), 3)",
      "multiply((-2, -2), 3)",
      "multiply((2, 1), 3)",
      "multiply((0, -1), 3)",
      "multiply((-1, 1), 3)",
      "multiply((-2, 2), 3)",
      "multiply((-1, -2), 3)",
      "multiply((-1, -1), 3)",
      "multiply((-2, 0), 3)",
      "multiply((1, 2), 3)",
      "multiply((0, 2), 3)",
      "multiply((1, -1), 3)",
      "multiply((-1, 2), 3)",
      "multiply((0, 0), 3)"
    ]
  },
  "merge_f": {
    "calls": 4,
    "execution_time": 0.0,
    "call_sites": {
      "solvers.py:2708": {
        "count": 4,
        "signatures": [
          {
            "type_signature": "merge_f(frozenset)",
            "value_signature": "merge_f(frozenset({frozenset({(1, (6, 2)), (1, (3, 5)), (1)"
          },
          {
            "type_signature": "merge_f(frozenset)",
            "value_signature": "merge_f(frozenset({frozenset({(2, (0, 0))}), frozenset({(8)"
          },
          {
            "type_signature": "merge_f(frozenset)",
            "value_signature": "merge_f(frozenset({frozenset({(3, (4, 1)), (3, (0, 5)), (3)"
          },
          {
            "type_signature": "merge_f(frozenset)",
            "value_signature": "merge_f(frozenset({frozenset({(2, (2, 4)), (2, (1, 5)), (2)"
          }
        ],
        "code_context": "x6 = merge_f(x1)"
      }
    },
    "type_signatures": [
      "merge_f(frozenset)"
    ],
    "value_signatures": [
      "merge_f(frozenset({frozenset({(3, (4, 1)), (3, (0, 5)), (3)",
      "merge_f(frozenset({frozenset({(2, (2, 4)), (2, (1, 5)), (2)",
      "merge_f(frozenset({frozenset({(1, (6, 2)), (1, (3, 5)), (1)",
      "merge_f(frozenset({frozenset({(2, (0, 0))}), frozenset({(8)"
    ]
  },
  "lbind": {
    "calls": 4,
    "execution_time": 0.0,
    "call_sites": {
      "solvers.py:2709": {
        "count": 4,
        "signatures": [
          {
            "type_signature": "lbind(function, frozenset)",
            "value_signature": "lbind(<function shift at 0x1007a2940>, frozenset(len=12))"
          },
          {
            "type_signature": "lbind(function, frozenset)",
            "value_signature": "lbind(<function shift at 0x1007a2940>, frozenset(len=6))"
          },
          {
            "type_signature": "lbind(function, frozenset)",
            "value_signature": "lbind(<function shift at 0x1007a2940>, frozenset(len=15))"
          },
          {
            "type_signature": "lbind(function, frozenset)",
            "value_signature": "lbind(<function shift at 0x1007a2940>, frozenset(len=11))"
          }
        ],
        "code_context": "x7 = lbind(shift, x6)"
      }
    },
    "type_signatures": [
      "lbind(function, frozenset)"
    ],
    "value_signatures": [
      "lbind(<function shift at 0x1007a2940>, frozenset(len=11))",
      "lbind(<function shift at 0x1007a2940>, frozenset(len=6))",
      "lbind(<function shift at 0x1007a2940>, frozenset(len=12))",
      "lbind(<function shift at 0x1007a2940>, frozenset(len=15))"
    ]
  },
  "shift": {
    "calls": 108,
    "execution_time": 0.0,
    "call_sites": {
      "solvers.py:2710": {
        "count": 100,
        "signatures": [
          {
            "type_signature": "shift(frozenset, tuple)",
            "value_signature": "shift(frozenset(len=12), (-3, -3))"
          },
          {
            "type_signature": "shift(frozenset, tuple)",
            "value_signature": "shift(frozenset(len=12), (-3, -6))"
          },
          {
            "type_signature": "shift(frozenset, tuple)",
            "value_signature": "shift(frozenset(len=12), (-3, 0))"
          },
          {
            "type_signature": "shift(frozenset, tuple)",
            "value_signature": "shift(frozenset(len=12), (-3, 3))"
          },
          {
            "type_signature": "shift(frozenset, tuple)",
            "value_signature": "shift(frozenset(len=12), (-3, 6))"
          },
          {
            "type_signature": "shift(frozenset, tuple)",
            "value_signature": "shift(frozenset(len=12), (3, -3))"
          },
          {
            "type_signature": "shift(frozenset, tuple)",
            "value_signature": "shift(frozenset(len=12), (3, -6))"
          },
          {
            "type_signature": "shift(frozenset, tuple)",
            "value_signature": "shift(frozenset(len=12), (3, 0))"
          },
          {
            "type_signature": "shift(frozenset, tuple)",
            "value_signature": "shift(frozenset(len=12), (-6, -3))"
          },
          {
            "type_signature": "shift(frozenset, tuple)",
            "value_signature": "shift(frozenset(len=12), (-6, -6))"
          },
          {
            "type_signature": "shift(frozenset, tuple)",
            "value_signature": "shift(frozenset(len=12), (-6, 0))"
          },
          {
            "type_signature": "shift(frozenset, tuple)",
            "value_signature": "shift(frozenset(len=12), (-6, 6))"
          },
          {
            "type_signature": "shift(frozenset, tuple)",
            "value_signature": "shift(frozenset(len=12), (3, 3))"
          },
          {
            "type_signature": "shift(frozenset, tuple)",
            "value_signature": "shift(frozenset(len=12), (3, 6))"
          },
          {
            "type_signature": "shift(frozenset, tuple)",
            "value_signature": "shift(frozenset(len=12), (-6, 3))"
          },
          {
            "type_signature": "shift(frozenset, tuple)",
            "value_signature": "shift(frozenset(len=12), (0, -3))"
          },
          {
            "type_signature": "shift(frozenset, tuple)",
            "value_signature": "shift(frozenset(len=12), (0, -6))"
          },
          {
            "type_signature": "shift(frozenset, tuple)",
            "value_signature": "shift(frozenset(len=12), (0, 0))"
          },
          {
            "type_signature": "shift(frozenset, tuple)",
            "value_signature": "shift(frozenset(len=12), (0, 3))"
          },
          {
            "type_signature": "shift(frozenset, tuple)",
            "value_signature": "shift(frozenset(len=12), (0, 6))"
          },
          {
            "type_signature": "shift(frozenset, tuple)",
            "value_signature": "shift(frozenset(len=12), (6, -6))"
          },
          {
            "type_signature": "shift(frozenset, tuple)",
            "value_signature": "shift(frozenset(len=12), (6, -3))"
          },
          {
            "type_signature": "shift(frozenset, tuple)",
            "value_signature": "shift(frozenset(len=12), (6, 0))"
          },
          {
            "type_signature": "shift(frozenset, tuple)",
            "value_signature": "shift(frozenset(len=12), (6, 6))"
          },
          {
            "type_signature": "shift(frozenset, tuple)",
            "value_signature": "shift(frozenset(len=12), (6, 3))"
          },
          {
            "type_signature": "shift(frozenset, tuple)",
            "value_signature": "shift(frozenset(len=6), (-3, -3))"
          },
          {
            "type_signature": "shift(frozenset, tuple)",
            "value_signature": "shift(frozenset(len=6), (-3, -6))"
          },
          {
            "type_signature": "shift(frozenset, tuple)",
            "value_signature": "shift(frozenset(len=6), (-3, 0))"
          },
          {
            "type_signature": "shift(frozenset, tuple)",
            "value_signature": "shift(frozenset(len=6), (-3, 3))"
          },
          {
            "type_signature": "shift(frozenset, tuple)",
            "value_signature": "shift(frozenset(len=6), (-3, 6))"
          },
          {
            "type_signature": "shift(frozenset, tuple)",
            "value_signature": "shift(frozenset(len=6), (3, -3))"
          },
          {
            "type_signature": "shift(frozenset, tuple)",
            "value_signature": "shift(frozenset(len=6), (3, -6))"
          },
          {
            "type_signature": "shift(frozenset, tuple)",
            "value_signature": "shift(frozenset(len=6), (3, 0))"
          },
          {
            "type_signature": "shift(frozenset, tuple)",
            "value_signature": "shift(frozenset(len=6), (-6, -3))"
          },
          {
            "type_signature": "shift(frozenset, tuple)",
            "value_signature": "shift(frozenset(len=6), (-6, -6))"
          },
          {
            "type_signature": "shift(frozenset, tuple)",
            "value_signature": "shift(frozenset(len=6), (-6, 0))"
          },
          {
            "type_signature": "shift(frozenset, tuple)",
            "value_signature": "shift(frozenset(len=6), (-6, 6))"
          },
          {
            "type_signature": "shift(frozenset, tuple)",
            "value_signature": "shift(frozenset(len=6), (3, 3))"
          },
          {
            "type_signature": "shift(frozenset, tuple)",
            "value_signature": "shift(frozenset(len=6), (3, 6))"
          },
          {
            "type_signature": "shift(frozenset, tuple)",
            "value_signature": "shift(frozenset(len=6), (-6, 3))"
          },
          {
            "type_signature": "shift(frozenset, tuple)",
            "value_signature": "shift(frozenset(len=6), (0, -3))"
          },
          {
            "type_signature": "shift(frozenset, tuple)",
            "value_signature": "shift(frozenset(len=6), (0, -6))"
          },
          {
            "type_signature": "shift(frozenset, tuple)",
            "value_signature": "shift(frozenset(len=6), (0, 0))"
          },
          {
            "type_signature": "shift(frozenset, tuple)",
            "value_signature": "shift(frozenset(len=6), (0, 3))"
          },
          {
            "type_signature": "shift(frozenset, tuple)",
            "value_signature": "shift(frozenset(len=6), (0, 6))"
          },
          {
            "type_signature": "shift(frozenset, tuple)",
            "value_signature": "shift(frozenset(len=6), (6, -6))"
          },
          {
            "type_signature": "shift(frozenset, tuple)",
            "value_signature": "shift(frozenset(len=6), (6, -3))"
          },
          {
            "type_signature": "shift(frozenset, tuple)",
            "value_signature": "shift(frozenset(len=6), (6, 0))"
          },
          {
            "type_signature": "shift(frozenset, tuple)",
            "value_signature": "shift(frozenset(len=6), (6, 6))"
          },
          {
            "type_signature": "shift(frozenset, tuple)",
            "value_signature": "shift(frozenset(len=6), (6, 3))"
          },
          {
            "type_signature": "shift(frozenset, tuple)",
            "value_signature": "shift(frozenset(len=15), (-3, -3))"
          },
          {
            "type_signature": "shift(frozenset, tuple)",
            "value_signature": "shift(frozenset(len=15), (-3, -6))"
          },
          {
            "type_signature": "shift(frozenset, tuple)",
            "value_signature": "shift(frozenset(len=15), (-3, 0))"
          },
          {
            "type_signature": "shift(frozenset, tuple)",
            "value_signature": "shift(frozenset(len=15), (-3, 3))"
          },
          {
            "type_signature": "shift(frozenset, tuple)",
            "value_signature": "shift(frozenset(len=15), (-3, 6))"
          },
          {
            "type_signature": "shift(frozenset, tuple)",
            "value_signature": "shift(frozenset(len=15), (3, -3))"
          },
          {
            "type_signature": "shift(frozenset, tuple)",
            "value_signature": "shift(frozenset(len=15), (3, -6))"
          },
          {
            "type_signature": "shift(frozenset, tuple)",
            "value_signature": "shift(frozenset(len=15), (3, 0))"
          },
          {
            "type_signature": "shift(frozenset, tuple)",
            "value_signature": "shift(frozenset(len=15), (-6, -3))"
          },
          {
            "type_signature": "shift(frozenset, tuple)",
            "value_signature": "shift(frozenset(len=15), (-6, -6))"
          },
          {
            "type_signature": "shift(frozenset, tuple)",
            "value_signature": "shift(frozenset(len=15), (-6, 0))"
          },
          {
            "type_signature": "shift(frozenset, tuple)",
            "value_signature": "shift(frozenset(len=15), (-6, 6))"
          },
          {
            "type_signature": "shift(frozenset, tuple)",
            "value_signature": "shift(frozenset(len=15), (3, 3))"
          },
          {
            "type_signature": "shift(frozenset, tuple)",
            "value_signature": "shift(frozenset(len=15), (3, 6))"
          },
          {
            "type_signature": "shift(frozenset, tuple)",
            "value_signature": "shift(frozenset(len=15), (-6, 3))"
          },
          {
            "type_signature": "shift(frozenset, tuple)",
            "value_signature": "shift(frozenset(len=15), (0, -3))"
          },
          {
            "type_signature": "shift(frozenset, tuple)",
            "value_signature": "shift(frozenset(len=15), (0, -6))"
          },
          {
            "type_signature": "shift(frozenset, tuple)",
            "value_signature": "shift(frozenset(len=15), (0, 0))"
          },
          {
            "type_signature": "shift(frozenset, tuple)",
            "value_signature": "shift(frozenset(len=15), (0, 3))"
          },
          {
            "type_signature": "shift(frozenset, tuple)",
            "value_signature": "shift(frozenset(len=15), (0, 6))"
          },
          {
            "type_signature": "shift(frozenset, tuple)",
            "value_signature": "shift(frozenset(len=15), (6, -6))"
          },
          {
            "type_signature": "shift(frozenset, tuple)",
            "value_signature": "shift(frozenset(len=15), (6, -3))"
          },
          {
            "type_signature": "shift(frozenset, tuple)",
            "value_signature": "shift(frozenset(len=15), (6, 0))"
          },
          {
            "type_signature": "shift(frozenset, tuple)",
            "value_signature": "shift(frozenset(len=15), (6, 6))"
          },
          {
            "type_signature": "shift(frozenset, tuple)",
            "value_signature": "shift(frozenset(len=15), (6, 3))"
          },
          {
            "type_signature": "shift(frozenset, tuple)",
            "value_signature": "shift(frozenset(len=11), (-3, -3))"
          },
          {
            "type_signature": "shift(frozenset, tuple)",
            "value_signature": "shift(frozenset(len=11), (-3, -6))"
          },
          {
            "type_signature": "shift(frozenset, tuple)",
            "value_signature": "shift(frozenset(len=11), (-3, 0))"
          },
          {
            "type_signature": "shift(frozenset, tuple)",
            "value_signature": "shift(frozenset(len=11), (-3, 3))"
          },
          {
            "type_signature": "shift(frozenset, tuple)",
            "value_signature": "shift(frozenset(len=11), (-3, 6))"
          },
          {
            "type_signature": "shift(frozenset, tuple)",
            "value_signature": "shift(frozenset(len=11), (3, -3))"
          },
          {
            "type_signature": "shift(frozenset, tuple)",
            "value_signature": "shift(frozenset(len=11), (3, -6))"
          },
          {
            "type_signature": "shift(frozenset, tuple)",
            "value_signature": "shift(frozenset(len=11), (3, 0))"
          },
          {
            "type_signature": "shift(frozenset, tuple)",
            "value_signature": "shift(frozenset(len=11), (-6, -3))"
          },
          {
            "type_signature": "shift(frozenset, tuple)",
            "value_signature": "shift(frozenset(len=11), (-6, -6))"
          },
          {
            "type_signature": "shift(frozenset, tuple)",
            "value_signature": "shift(frozenset(len=11), (-6, 0))"
          },
          {
            "type_signature": "shift(frozenset, tuple)",
            "value_signature": "shift(frozenset(len=11), (-6, 6))"
          },
          {
            "type_signature": "shift(frozenset, tuple)",
            "value_signature": "shift(frozenset(len=11), (3, 3))"
          },
          {
            "type_signature": "shift(frozenset, tuple)",
            "value_signature": "shift(frozenset(len=11), (3, 6))"
          },
          {
            "type_signature": "shift(frozenset, tuple)",
            "value_signature": "shift(frozenset(len=11), (-6, 3))"
          },
          {
            "type_signature": "shift(frozenset, tuple)",
            "value_signature": "shift(frozenset(len=11), (0, -3))"
          },
          {
            "type_signature": "shift(frozenset, tuple)",
            "value_signature": "shift(frozenset(len=11), (0, -6))"
          },
          {
            "type_signature": "shift(frozenset, tuple)",
            "value_signature": "shift(frozenset(len=11), (0, 0))"
          },
          {
            "type_signature": "shift(frozenset, tuple)",
            "value_signature": "shift(frozenset(len=11), (0, 3))"
          },
          {
            "type_signature": "shift(frozenset, tuple)",
            "value_signature": "shift(frozenset(len=11), (0, 6))"
          },
          {
            "type_signature": "shift(frozenset, tuple)",
            "value_signature": "shift(frozenset(len=11), (6, -6))"
          },
          {
            "type_signature": "shift(frozenset, tuple)",
            "value_signature": "shift(frozenset(len=11), (6, -3))"
          },
          {
            "type_signature": "shift(frozenset, tuple)",
            "value_signature": "shift(frozenset(len=11), (6, 0))"
          },
          {
            "type_signature": "shift(frozenset, tuple)",
            "value_signature": "shift(frozenset(len=11), (6, 6))"
          },
          {
            "type_signature": "shift(frozenset, tuple)",
            "value_signature": "shift(frozenset(len=11), (6, 3))"
          }
        ],
        "code_context": "x8 = mapply(x7, x5)"
      },
      "solvers.py:2711": {
        "count": 4,
        "signatures": [
          {
            "type_signature": "shift(frozenset, tuple)",
            "value_signature": "shift(frozenset(len=252), (-1, 1))"
          },
          {
            "type_signature": "shift(frozenset, tuple)",
            "value_signature": "shift(frozenset(len=150), (-1, 1))"
          },
          {
            "type_signature": "shift(frozenset, tuple)",
            "value_signature": "shift(frozenset(len=279), (-1, 1))"
          },
          {
            "type_signature": "shift(frozenset, tuple)",
            "value_signature": "shift(frozenset(len=211), (-1, 1))"
          }
        ],
        "code_context": "x9 = shift(x8, UP_RIGHT)"
      },
      "solvers.py:2712": {
        "count": 4,
        "signatures": [
          {
            "type_signature": "shift(frozenset, tuple)",
            "value_signature": "shift(frozenset(len=252), (1, -1))"
          },
          {
            "type_signature": "shift(frozenset, tuple)",
            "value_signature": "shift(frozenset(len=150), (1, -1))"
          },
          {
            "type_signature": "shift(frozenset, tuple)",
            "value_signature": "shift(frozenset(len=279), (1, -1))"
          },
          {
            "type_signature": "shift(frozenset, tuple)",
            "value_signature": "shift(frozenset(len=211), (1, -1))"
          }
        ],
        "code_context": "x10 = shift(x8, DOWN_LEFT)"
      }
    },
    "type_signatures": [
      "shift(frozenset, tuple)"
    ],
    "value_signatures": [
      "shift(frozenset(len=6), (0, 3))",
      "shift(frozenset(len=15), (3, -3))",
      "shift(frozenset(len=11), (3, 0))",
      "shift(frozenset(len=150), (-1, 1))",
      "shift(frozenset(len=12), (0, 6))",
      "shift(frozenset(len=12), (6, 6))",
      "shift(frozenset(len=6), (0, 0))",
      "shift(frozenset(len=12), (3, 6))",
      "shift(frozenset(len=11), (3, -6))",
      "shift(frozenset(len=15), (0, 3))",
      "shift(frozenset(len=15), (-3, -6))",
      "shift(frozenset(len=6), (6, 3))",
      "shift(frozenset(len=252), (1, -1))",
      "shift(frozenset(len=11), (-3, 3))",
      "shift(frozenset(len=15), (6, -3))",
      "shift(frozenset(len=6), (6, -6))",
      "shift(frozenset(len=11), (-6, -3))",
      "shift(frozenset(len=15), (3, 6))",
      "shift(frozenset(len=11), (6, -3))",
      "shift(frozenset(len=15), (0, 6))",
      "shift(frozenset(len=11), (0, -3))",
      "shift(frozenset(len=12), (3, 3))",
      "shift(frozenset(len=15), (3, 0))",
      "shift(frozenset(len=12), (3, -3))",
      "shift(frozenset(len=11), (-3, -6))",
      "shift(frozenset(len=6), (0, -3))",
      "shift(frozenset(len=6), (6, -3))",
      "shift(frozenset(len=6), (-3, -3))",
      "shift(frozenset(len=11), (-6, 6))",
      "shift(frozenset(len=12), (-3, 3))",
      "shift(frozenset(len=15), (0, -3))",
      "shift(frozenset(len=11), (0, 0))",
      "shift(frozenset(len=12), (0, -6))",
      "shift(frozenset(len=6), (-3, 6))",
      "shift(frozenset(len=6), (0, 6))",
      "shift(frozenset(len=6), (6, 6))",
      "shift(frozenset(len=12), (6, -3))",
      "shift(frozenset(len=15), (6, -6))",
      "shift(frozenset(len=11), (-6, 3))",
      "shift(frozenset(len=15), (-6, -3))",
      "shift(frozenset(len=6), (-3, 0))",
      "shift(frozenset(len=6), (0, -6))",
      "shift(frozenset(len=11), (0, -6))",
      "shift(frozenset(len=12), (0, 3))",
      "shift(frozenset(len=15), (-3, -3))",
      "shift(frozenset(len=15), (6, 6))",
      "shift(frozenset(len=12), (0, 0))",
      "shift(frozenset(len=12), (-3, 6))",
      "shift(frozenset(len=11), (3, 6))",
      "shift(frozenset(len=6), (3, 6))",
      "shift(frozenset(len=6), (-3, -6))",
      "shift(frozenset(len=11), (-3, -3))",
      "shift(frozenset(len=12), (-6, -3))",
      "shift(frozenset(len=12), (-6, 6))",
      "shift(frozenset(len=15), (3, -6))",
      "shift(frozenset(len=12), (-6, -6))",
      "shift(frozenset(len=11), (6, 3))",
      "shift(frozenset(len=279), (-1, 1))",
      "shift(frozenset(len=15), (-3, 3))",
      "shift(frozenset(len=12), (-3, 0))",
      "shift(frozenset(len=150), (1, -1))",
      "shift(frozenset(len=6), (-3, 3))",
      "shift(frozenset(len=12), (6, 0))",
      "shift(frozenset(len=12), (6, 3))",
      "shift(frozenset(len=6), (3, -3))",
      "shift(frozenset(len=211), (1, -1))",
      "shift(frozenset(len=12), (-3, -6))",
      "shift(frozenset(len=11), (-3, 0))",
      "shift(frozenset(len=6), (-6, -6))",
      "shift(frozenset(len=6), (-6, 6))",
      "shift(frozenset(len=12), (0, -3))",
      "shift(frozenset(len=15), (-6, 6))",
      "shift(frozenset(len=11), (6, -6))",
      "shift(frozenset(len=15), (-3, 0))",
      "shift(frozenset(len=12), (-6, 0))",
      "shift(frozenset(len=11), (6, 0))",
      "shift(frozenset(len=11), (-6, 0))",
      "shift(frozenset(len=6), (-6, 3))",
      "shift(frozenset(len=15), (6, 0))",
      "shift(frozenset(len=6), (3, 0))",
      "shift(frozenset(len=11), (-3, 6))",
      "shift(frozenset(len=11), (0, 3))",
      "shift(frozenset(len=15), (6, 3))",
      "shift(frozenset(len=15), (0, 0))",
      "shift(frozenset(len=11), (6, 6))",
      "shift(frozenset(len=15), (-3, 6))",
      "shift(frozenset(len=279), (1, -1))",
      "shift(frozenset(len=11), (0, 6))",
      "shift(frozenset(len=15), (3, 3))",
      "shift(frozenset(len=12), (3, 0))",
      "shift(frozenset(len=6), (3, 3))",
      "shift(frozenset(len=15), (-6, 0))",
      "shift(frozenset(len=11), (3, 3))",
      "shift(frozenset(len=12), (-3, -3))",
      "shift(frozenset(len=252), (-1, 1))",
      "shift(frozenset(len=15), (-6, -6))",
      "shift(frozenset(len=12), (-6, 3))",
      "shift(frozenset(len=12), (3, -6))",
      "shift(frozenset(len=6), (3, -6))",
      "shift(frozenset(len=6), (-6, 0))",
      "shift(frozenset(len=11), (-6, -6))",
      "shift(frozenset(len=15), (0, -6))",
      "shift(frozenset(len=6), (6, 0))",
      "shift(frozenset(len=211), (-1, 1))",
      "shift(frozenset(len=12), (6, -6))",
      "shift(frozenset(len=11), (3, -3))",
      "shift(frozenset(len=15), (-6, 3))",
      "shift(frozenset(len=6), (-6, -3))"
    ]
  },
  "paint": {
    "calls": 12,
    "execution_time": 0.0,
    "call_sites": {
      "solvers.py:2713": {
        "count": 4,
        "signatures": [
          {
            "type_signature": "paint(tuple, frozenset)",
            "value_signature": "paint(tuple(len=7), frozenset(len=252))"
          },
          {
            "type_signature": "paint(tuple, frozenset)",
            "value_signature": "paint(tuple(len=7), frozenset(len=150))"
          },
          {
            "type_signature": "paint(tuple, frozenset)",
            "value_signature": "paint(tuple(len=7), frozenset(len=279))"
          },
          {
            "type_signature": "paint(tuple, frozenset)",
            "value_signature": "paint(tuple(len=7), frozenset(len=211))"
          }
        ],
        "code_context": "x11 = paint(I, x8)"
      },
      "solvers.py:2714": {
        "count": 4,
        "signatures": [
          {
            "type_signature": "paint(tuple, frozenset)",
            "value_signature": "paint(tuple(len=7), frozenset(len=252))"
          },
          {
            "type_signature": "paint(tuple, frozenset)",
            "value_signature": "paint(tuple(len=7), frozenset(len=150))"
          },
          {
            "type_signature": "paint(tuple, frozenset)",
            "value_signature": "paint(tuple(len=7), frozenset(len=279))"
          },
          {
            "type_signature": "paint(tuple, frozenset)",
            "value_signature": "paint(tuple(len=7), frozenset(len=211))"
          }
        ],
        "code_context": "x12 = paint(x11, x9)"
      },
      "solvers.py:2715": {
        "count": 4,
        "signatures": [
          {
            "type_signature": "paint(tuple, frozenset)",
            "value_signature": "paint(tuple(len=7), frozenset(len=252))"
          },
          {
            "type_signature": "paint(tuple, frozenset)",
            "value_signature": "paint(tuple(len=7), frozenset(len=150))"
          },
          {
            "type_signature": "paint(tuple, frozenset)",
            "value_signature": "paint(tuple(len=7), frozenset(len=279))"
          },
          {
            "type_signature": "paint(tuple, frozenset)",
            "value_signature": "paint(tuple(len=7), frozenset(len=211))"
          }
        ],
        "code_context": "O = paint(x12, x10)"
      }
    },
    "type_signatures": [
      "paint(tuple, frozenset)"
    ],
    "value_signatures": [
      "paint(tuple(len=7), frozenset(len=252))",
      "paint(tuple(len=7), frozenset(len=211))",
      "paint(tuple(len=7), frozenset(len=279))",
      "paint(tuple(len=7), frozenset(len=150))"
    ]
  }
}