{
  "summary": {
    "total_functions": 10,
    "dsl_functions": 10,
    "non_dsl_functions": 0,
    "functions_with_t_variants": 1,
    "functions_with_f_variants": 1,
    "threshold_percent": 100.0
  },
  "specialized_functions": [
    {
      "name": "last",
      "total_calls": 108,
      "tuple_percent": 100.0,
      "has_tuple_variant": true,
      "frozenset_percent": 0.0,
      "has_frozenset_variant": true,
      "meets_threshold": true,
      "call_sites": {
        "solvers.py:952": {
          "count": 49,
          "code_context": "x6 = sfilter_f(x1, x5)",
          "tuple_calls": 49,
          "frozenset_calls": 0
        }
      }
    }
  ],
  "high_impact_opportunities": [
    {
      "name": "last",
      "variant": "last_t",
      "type": "tuple",
      "percent": 100.0,
      "calls": 108,
      "call_sites": {
        "solvers.py:952": {
          "count": 49,
          "code_context": "x6 = sfilter_f(x1, x5)"
        }
      }
    }
  ],
  "perfect_matches": [
    {
      "name": "last",
      "variant": "last_t",
      "type": "tuple",
      "calls": 108,
      "call_sites": {
        "solvers.py:952": {
          "count": 49,
          "code_context": "x6 = sfilter_f(x1, x5)"
        }
      }
    }
  ],
  "analyzed_functions": [
    "asindices",
    "width_t",
    "halve",
    "matcher",
    "compose",
    "sfilter_f",
    "last",
    "flip",
    "fill",
    "toindices"
  ]
}